{
  "headers": {
    "age": "11480679",
    "etag": "\"15d2f23e9100358244cd927f35f507e5\"",
    "server": "deno/gcp-europe-north1",
    "x-amz-cf-id": "rr2n_uoTzXxBYuVCZuF5EhLjmhgA1fLiGSvpiujvxsOWKB5BFnpsUQ==",
    "server-timing": "fetchSource;dur=364",
    "vary": "Accept-Encoding, Origin",
    "last-modified": "Fri, 25 Mar 2022 13:32:48 GMT",
    "x-frame-options": "DENY",
    "via": "http/2 edgeproxy-h",
    "x-amz-replication-status": "COMPLETED",
    "x-amz-cf-pop": "HEL51-P2",
    "x-cache": "Hit from cloudfront",
    "content-security-policy": "default-src 'none'; style-src 'unsafe-inline'; sandbox",
    "x-content-type-options": "nosniff",
    "strict-transport-security": "max-age=63072000; includeSubDomains; preload",
    "accept-ranges": "bytes",
    "content-length": "5703",
    "referrer-policy": "strict-origin-when-cross-origin",
    "x-amz-version-id": "OR8L8PlUjW4Mc2TYpdri5d2_gB6RQlk5",
    "date": "Sun, 23 Apr 2023 07:34:29 GMT",
    "content-type": "application/typescript; charset=utf-8",
    "cross-origin-embedder-policy": "same-origin",
    "cache-control": "public, max-age=31536000, immutable",
    "cross-origin-resource-policy": "same-origin",
    "access-control-allow-origin": "*",
    "cross-origin-opener-policy": "same-origin"
  },
  "url": "https://deno.land/std@0.132.0/node/_fs/_fs_common.ts",
  "now": {
    "secs_since_epoch": 1693715948,
    "nanos_since_epoch": 643260697
  }
}